chemsynthcalc/__init__.py
chemsynthcalc/balancer.py
chemsynthcalc/balancing_algos.py
chemsynthcalc/chem_errors.py
chemsynthcalc/chem_output.py
chemsynthcalc/chemical_formula.py
chemsynthcalc/chemical_reaction.py
chemsynthcalc/coefs.py
chemsynthcalc/formula.py
chemsynthcalc/formula_parser.py
chemsynthcalc/formula_validator.py
chemsynthcalc/molar_mass.py
chemsynthcalc/periodic_table.py
chemsynthcalc/reaction.py
chemsynthcalc/reaction_decomposer.py
chemsynthcalc/reaction_matrix.py
chemsynthcalc/reaction_validator.py
chemsynthcalc/utils.py
chemsynthcalc/version.py
chemsynthcalc-2.0.1.dist-info/METADATA
chemsynthcalc-2.0.1.dist-info/WHEEL
chemsynthcalc-2.0.1.dist-info/licenses/LICENSE
chemsynthcalc-2.0.1.dist-info/RECORD
