Metadata-Version: 2.4
Name: chemsynthcalc
Version: 2.0.1
Summary: Python package for calculating the masses of substances required for chemical synthesis directly from the reaction string. It includes solutions for all intermidiate steps, including chemical formula parsing, molar mass calculation and reaction balancing with different matrix methods.
Author-email: Egor Syrov <syrov_ev@mail.ru>
License: MIT License
License-File: LICENSE
Classifier: License :: OSI Approved :: MIT License
Classifier: Operating System :: OS Independent
Classifier: Programming Language :: Python :: 3
Requires-Python: >=3.10
Requires-Dist: scipy>1.15
